cibyl/__init__.py
cibyl/config.py
cibyl/orchestrator.py
cibyl/publisher.py
cibyl/_data/schemas/config.json
cibyl/cli/__init__.py
cibyl/cli/argument.py
cibyl/cli/interactions.py
cibyl/cli/main.py
cibyl/cli/output.py
cibyl/cli/parser.py
cibyl/cli/query.py
cibyl/cli/ranged_argument.py
cibyl/cli/validator.py
cibyl/exceptions/__init__.py
cibyl/exceptions/cli.py
cibyl/exceptions/config.py
cibyl/exceptions/elasticsearch.py
cibyl/exceptions/features.py
cibyl/exceptions/git.py
cibyl/exceptions/jenkins.py
cibyl/exceptions/jenkins_job_builder.py
cibyl/exceptions/model.py
cibyl/exceptions/plugin.py
cibyl/exceptions/source.py
cibyl/exceptions/zuul.py
cibyl/features/__init__.py
cibyl/features/general.py
cibyl/models/__init__.py
cibyl/models/attribute.py
cibyl/models/model.py
cibyl/models/ci/__init__.py
cibyl/models/ci/system_factory.py
cibyl/models/ci/base/__init__.py
cibyl/models/ci/base/build.py
cibyl/models/ci/base/environment.py
cibyl/models/ci/base/job.py
cibyl/models/ci/base/stage.py
cibyl/models/ci/base/system.py
cibyl/models/ci/base/test.py
cibyl/models/ci/zuul/__init__.py
cibyl/models/ci/zuul/build.py
cibyl/models/ci/zuul/job.py
cibyl/models/ci/zuul/pipeline.py
cibyl/models/ci/zuul/project.py
cibyl/models/ci/zuul/system.py
cibyl/models/ci/zuul/tenant.py
cibyl/models/ci/zuul/test.py
cibyl/models/ci/zuul/test_suite.py
cibyl/models/product/__init__.py
cibyl/models/product/feature.py
cibyl/outputs/__init__.py
cibyl/outputs/cli/__init__.py
cibyl/outputs/cli/printer.py
cibyl/outputs/cli/ci/__init__.py
cibyl/outputs/cli/ci/_docs/printing/colored.puml
cibyl/outputs/cli/ci/_docs/printing/serialized.puml
cibyl/outputs/cli/ci/env/__init__.py
cibyl/outputs/cli/ci/env/factory.py
cibyl/outputs/cli/ci/env/printer.py
cibyl/outputs/cli/ci/env/impl/__init__.py
cibyl/outputs/cli/ci/env/impl/colored.py
cibyl/outputs/cli/ci/env/impl/serialized.py
cibyl/outputs/cli/ci/system/__init__.py
cibyl/outputs/cli/ci/system/printer.py
cibyl/outputs/cli/ci/system/common/__init__.py
Cibyl-1.0.0.dist-info/LICENSE
Cibyl-1.0.0.dist-info/METADATA
Cibyl-1.0.0.dist-info/WHEEL
Cibyl-1.0.0.dist-info/entry_points.txt
Cibyl-1.0.0.dist-info/pbr.json
Cibyl-1.0.0.dist-info/top_level.txt
Cibyl-1.0.0.dist-info/RECORD
