Metadata-Version: 2.1
Name: Cibyl
Version: 1.0.0
Summary: UNKNOWN
Home-page: https://github.com/rhos-infra/cibyl
Author: Red Hat Code Reliability Engineering Team
Author-email: rhos-cre@redhat.com
Maintainer: Red Hat Code Reliability Engineering Team
Maintainer-email: rhos-cre@redhat.com
License: UNKNOWN
Platform: UNKNOWN
Classifier: Intended Audience :: Developers
Classifier: Intended Audience :: Information Technology
Classifier: Intended Audience :: System Administrators
Classifier: License :: OSI Approved :: Apache Software License
Classifier: Operating System :: OS Independent
Classifier: Programming Language :: Python
Classifier: Programming Language :: Python :: 3
Classifier: Topic :: Software Development :: Libraries :: Python Modules
License-File: LICENSE
Requires-Dist: wheel (>=0.37.1)
Requires-Dist: pyyaml (>=5.0)
Requires-Dist: requests (~=2.27.1)
Requires-Dist: elasticsearch (~=7.17.1)
Requires-Dist: colorlog (~=6.6.0)
Requires-Dist: urllib3 (~=1.26.9)
Requires-Dist: rfc3987 (~=1.3.8)
Requires-Dist: overrides (~=6.1.0)
Requires-Dist: GitPython (~=3.1.18)
Requires-Dist: deprecation (~=2.1.0)
Requires-Dist: jsonschema (~=3.2.0)
Requires-Dist: python-dateutil (~=2.8.2)
Requires-Dist: PyGithub (~=1.55)
Requires-Dist: validators (~=0.20.0)
Requires-Dist: cached-property (~=1.5.2)
Requires-Dist: xsdata (~=22.7)
Requires-Dist: StrEnum (~=0.4.8)
Requires-Dist: pbr (>=2.0.0)
Requires-Dist: dataclasses (~=0.8) ; (python_version<='3.6')
Requires-Dist: networkx (==2.5.1) ; (python_version<='3.6')
Requires-Dist: networkx (~=2.8.4) ; (python_version>'3.6')
